{"Administration.NewAccount":{"p":[],"a":[]},"Administration.NewWebServiceAccount":{"p":[],"a":[]},"Administration.RetrieveTimeZones":{"p":[],"a":[]},"Administration.ShowPasswordForm":{"p":["Administration.Account"],"a":[]},"Administration.ChangePassword":{"p":["Administration.AccountPasswordData"],"a":[["Administration.AccountPasswordData_Account","Administration.AccountPasswordData"]]},"Administration.SaveNewAccount":{"p":["Administration.AccountPasswordData"],"a":[["Administration.AccountPasswordData_Account","Administration.AccountPasswordData"]]},"Administration.ShowMyPasswordForm":{"p":["Administration.Account"],"a":[]},"Administration.ChangeMyPassword":{"p":["Administration.AccountPasswordData"],"a":[["Administration.AccountPasswordData_Account","Administration.AccountPasswordData"]]},"Rencar.ACT_Contract_Search":{"p":["Rencar.ContractSearch"],"a":[["Rencar.Contract_ContractSearch","Rencar.ContractSearch"],["Rencar.Contract_ContractSearch","Rencar.Contract"]]},"Rencar.ACT_Contract_ExportToExcell":{"p":["Rencar.ContractSearch"],"a":null},"Rencar.DS_ContractSearch":{"p":[],"a":[]},"Rencar.ACT_CarSearch_Filter":{"p":["Rencar.CarSearch"],"a":[["Rencar.CarSearch_VehicleUnit","MasterData.VehicleUnit"],["Rencar.CarSearch_VehicleUnit","Rencar.CarSearch"]]},"Rencar.ACT_Contract_New":{"p":["MasterData.VehicleUnit"],"a":[["MasterData.VehicleUnit_Vehicle","MasterData.VehicleUnit"]]},"Rencar.DS_CarSearch":{"p":[],"a":[]},"Rencar.ACT_Contract_DeliverToday":{"p":["Rencar.Contract"],"a":[]},"Rencar.ACT_Login_SignUp_New":{"p":[],"a":[]},"Rencar.ACT_SignUp_Save":{"p":["Rencar.SignUp"],"a":[]},"Rencar.ACT_DeliveryAddress_New":{"p":["Administration.Account"],"a":[]},"Rencar.ACT_DeliveryAddress_Del":{"p":["Rencar.DeliveryAddress","Administration.Account"],"a":[]},"Rencar.OCH_DeliveryAddress_GetPostalCode":{"p":["Rencar.DeliveryAddress"],"a":[]},"Rencar.ACT_DeliveryAddress_Save":{"p":["Rencar.DeliveryAddress"],"a":[]},"Rencar.OCH_Contract_Date":{"p":["Rencar.Contract"],"a":[]},"Rencar.ACT_Contract_Save":{"p":["Rencar.Contract"],"a":null},"Rencar.ACT_Contract_Postpone_Save":{"p":["Rencar.Contract"],"a":[["Rencar.Contract_VehicleUnit","Rencar.Contract"]]},"Rencar.DS_Value":{"p":["Rencar.DashboardHelper"],"a":[["Rencar.Value_DashboardHelper","Rencar.DashboardHelper"]]},"Rencar.ACT_DashboardHelper_Save":{"p":["Rencar.DashboardHelper"],"a":[["Rencar.Value_DashboardHelper","Rencar.DashboardHelper"]]},"MasterData.ACT_Brand_Save":{"p":["MasterData.Brand"],"a":[]},"MasterData.ACT_Vehicle_New":{"p":[],"a":[]},"MasterData.ACT_Motorcycle_New":{"p":[],"a":[]},"MasterData.ACT_Vehicle_Edit":{"p":["MasterData.Vehicle"],"a":[["MasterData.VehiclePicture_Vehicle","MasterData.Vehicle"],["MasterData.VehiclePicture_Vehicle","MasterData.VehiclePicture"]]},"MasterData.ACT_Vehicle_SendToService":{"p":["MasterData.Vehicle"],"a":[["MasterData.Vehicle_Brand","MasterData.Vehicle"]]},"MasterData.ACT_Vehicle_NewImport":{"p":[],"a":[]},"MasterData.ACT_Vehicle_Save":{"p":["MasterData.Vehicle"],"a":[["MasterData.Vehicle_Brand","MasterData.Vehicle"],["MasterData.VehiclePicture_Vehicle","MasterData.Vehicle"]]},"MasterData.ACT_TemplateDocument_Vehicle_Save":{"p":["ExcelImporter.TemplateDocument"],"a":null},"MasterData.ACT_VehicleUnit_Save":{"p":["MasterData.VehicleUnit"],"a":[["MasterData.VehicleUnit_Vehicle","MasterData.VehicleUnit"]]},"MasterData.ACT_State_Sync":{"p":[],"a":[]},"MasterData.ACT_City_Sync":{"p":[],"a":[]},"MxModelReflection.IVK_SyncObjects":{"p":[],"a":[]},"MxModelReflection.IVK_ToggleModule":{"p":["MxModelReflection.Module"],"a":[]},"MxModelReflection.DSL_Modules":{"p":[],"a":[]},"MxModelReflection.IVK_MxObjectTypeCommit":{"p":["MxModelReflection.MxObjectType"],"a":[]},"MxModelReflection.DSO_InheritsFromContainer":{"p":["MxModelReflection.MxObjectType"],"a":[["MxModelReflection.MxObjectType_SubClassOf_MxObjectType","MxModelReflection.MxObjectType"]]},"MxModelReflection.MB_TestThePattern":{"p":["MxModelReflection.TestPattern"],"a":null},"MxModelReflection.Ch_ObjectTypeStart":{"p":["MxModelReflection.Token"],"a":[["MxModelReflection.Token_MxObjectType_Start","MxModelReflection.Token"]]},"MxModelReflection.Ch_FindReference":{"p":["MxModelReflection.Token"],"a":[["MxModelReflection.Token_MxObjectType_Start","MxModelReflection.Token"]]},"MxModelReflection.Ch_Reference":{"p":["MxModelReflection.Token"],"a":[["MxModelReflection.Token_MxObjectReference","MxModelReflection.Token"]]},"MxModelReflection.Ch_FindObjectTypeReference":{"p":["MxModelReflection.Token"],"a":[["MxModelReflection.Token_MxObjectReference","MxModelReflection.Token"]]},"MxModelReflection.Ch_ObjecttypeReference":{"p":["MxModelReflection.Token"],"a":[["MxModelReflection.Token_MxObjectType_Referenced","MxModelReflection.Token"]]},"MxModelReflection.Ch_FindMemberReference":{"p":["MxModelReflection.Token"],"a":[["MxModelReflection.Token_MxObjectType_Referenced","MxModelReflection.Token"]]},"MxModelReflection.Ch_Member":{"p":["MxModelReflection.Token"],"a":[["MxModelReflection.Token_MxObjectMember","MxModelReflection.Token"]]},"MxModelReflection.Ch_FindMember":{"p":["MxModelReflection.Token"],"a":[["MxModelReflection.Token_MxObjectType_Start","MxModelReflection.Token"]]},"MxModelReflection.MB_TestTokenPattern":{"p":["MxModelReflection.Token"],"a":[]},"MxModelReflection.OC_FindObjectType":{"p":["MxModelReflection.DbSizeEstimate"],"a":[]},"MxModelReflection.IVK_RecalculateSize":{"p":[],"a":[]},"MxModelReflection.IVK_OpenReferencedMendixObject":{"p":["MxModelReflection.MxObjectReference","MxModelReflection.MxObjectType"],"a":[["MxModelReflection.MxObjectReference_MxObjectType","MxModelReflection.MxObjectReference"]]},"System.ShowHomePage":{"p":[],"a":[]},"Encryption.MB_SaveCertificate":{"p":["Encryption.PGPCertificate"],"a":null},"Encryption.MB_GenerateCertificate":{"p":["Encryption.PGPCertificate"],"a":null},"Encryption.MB_ChangePasswordSave":{"p":["Encryption.PasswordData"],"a":[["Encryption.PasswordData_ExampleConfiguration","Encryption.PasswordData"]]},"Encryption.MB_ShowChangePassword":{"p":["Encryption.ExampleConfiguration"],"a":[]},"Encryption.MB_GenerateKeyShowPage":{"p":[],"a":[]},"Encryption.MB_NewPubKey":{"p":[],"a":[]},"Encryption.MB_NewPrivateKey":{"p":[],"a":[]},"Encryption.MB_OpenCertificateDetails":{"p":["Encryption.PGPCertificate"],"a":[]},"EmailTemplate.IVK_DuplicateEmailTemplate":{"p":["EmailTemplate.EmailTemplate"],"a":[["EmailTemplate.EmailTemplate_Token","EmailTemplate.EmailTemplate"]]},"EmailTemplate.IVK_ResendFailedEmails":{"p":["EmailTemplate.Email"],"a":[]},"EmailTemplate.IVK_SaveEmailSettings":{"p":["EmailTemplate.EmailSettings"],"a":[["EmailTemplate.Token_EmailSettings","EmailTemplate.EmailSettings"]]},"EmailTemplate.IVK_CreateTestMessage":{"p":["EmailTemplate.EmailSettings"],"a":[]},"EmailTemplate.DS_GetEmailSettings":{"p":[],"a":[]},"EmailTemplate.SE_Cleanup":{"p":[],"a":[]},"EmailTemplate.SE_SendQueuedEmails":{"p":[],"a":[]},"EmailTemplate.DS_CheckForSetup":{"p":[],"a":[]},"EmailTemplate.OCH_isOAuthUsed":{"p":["EmailTemplate.EmailSettings"],"a":[["EmailTemplate.EmailSettings_OAuthProviderDetails","EmailTemplate.EmailSettings"]]},"EmailTemplate.OCh_SSL":{"p":["EmailTemplate.EmailSettings"],"a":[]},"EmailTemplate.OCh_TLS":{"p":["EmailTemplate.EmailSettings"],"a":[]},"EmailTemplate.IVK_ChangePortSSL":{"p":["EmailTemplate.EmailSettings"],"a":[]},"EmailTemplate.IVK_SaveEmailSettingsFromTestMessage":{"p":["EmailTemplate.TestMessage"],"a":[["EmailTemplate.TestMessage_EmailSettings","EmailTemplate.TestMessage"],["EmailTemplate.Token_EmailSettings","EmailTemplate.EmailSettings"]]},"EmailTemplate.IVK_SendTestMessage":{"p":["EmailTemplate.TestMessage"],"a":null},"EmailTemplate.IVK_ChangePortTLS":{"p":["EmailTemplate.EmailSettings"],"a":[]},"EmailTemplate.IVK_SaveEmailTemplate":{"p":["EmailTemplate.EmailTemplate"],"a":[["EmailTemplate.EmailTemplate_Token","EmailTemplate.EmailTemplate"],["MxModelReflection.Token_MxObjectType_Start","MxModelReflection.Token"],["MxModelReflection.Token_MxObjectReference","MxModelReflection.Token"],["MxModelReflection.Token_MxObjectType_Referenced","MxModelReflection.Token"],["MxModelReflection.Token_MxObjectMember","MxModelReflection.Token"]]},"EmailTemplate.IVK_GeneratePlainText":{"p":["EmailTemplate.EmailTemplate"],"a":[]},"EmailTemplate.IVK_OpenModelReflection":{"p":["EmailTemplate.EmailTemplate"],"a":[]},"EmailTemplate.IVK_Emailtemplate_NewToken":{"p":["EmailTemplate.EmailTemplate"],"a":[["EmailTemplate.EmailTemplate_Token","EmailTemplate.EmailTemplate"],["MxModelReflection.Token_MxObjectType_Start","MxModelReflection.Token"]]},"EmailTemplate.DS_LoadModelReflectionHelper":{"p":["EmailTemplate.EmailTemplate"],"a":[]},"EmailTemplate.IVK_CreateTestEmail":{"p":["EmailTemplate.ModuleSetup"],"a":[["EmailTemplate.ModuleSetup_EmailSettings","EmailTemplate.ModuleSetup"]]},"EmailTemplate.IVK_EmailSettingsWizard_edit":{"p":["EmailTemplate.TestMessage"],"a":[["EmailTemplate.TestMessage_ModuleSetup","EmailTemplate.TestMessage"]]},"EmailTemplate.IVK_SkipTestEmail":{"p":["EmailTemplate.TestMessage"],"a":[["EmailTemplate.TestMessage_ModuleSetup","EmailTemplate.TestMessage"],["EmailTemplate.ModuleSetup_EmailSettings","EmailTemplate.ModuleSetup"],["EmailTemplate.EmailSettings_OAuthProviderDetails","EmailTemplate.OAuthProviderDetails"],["EmailTemplate.EmailSettings_OAuthProviderDetails","EmailTemplate.EmailSettings"],["EmailTemplate.Token_EmailSettings","EmailTemplate.EmailSettings"],["EmailTemplate.Token_EmailSettings","EmailTemplate.Token"]]},"EmailTemplate.IVK_SaveStep1":{"p":["EmailTemplate.TestMessage"],"a":[["EmailTemplate.TestMessage_EmailSettings","EmailTemplate.TestMessage"],["EmailTemplate.TestMessage_ModuleSetup","EmailTemplate.TestMessage"]]},"EmailTemplate.DS_GetFirstTemplate":{"p":[],"a":[]},"EmailTemplate.IVK_SaveStep2":{"p":["EmailTemplate.ModuleSetup"],"a":[]},"EmailTemplate.IVK_DownloadAttachment":{"p":["EmailTemplate.Attachment"],"a":[]},"EmailTemplate.IVK_ResendFailedEmail":{"p":["EmailTemplate.Email"],"a":[]},"DeepLink.ACT_ShowMicroflowSelect":{"p":["DeepLink.DeepLink"],"a":[]},"DeepLink.DS_MicroflowByDeeplink":{"p":["DeepLink.DeepLink"],"a":[]},"DeepLink.ACT_DeleteDeepLink":{"p":["DeepLink.DeepLink"],"a":[]},"DeepLink.ACT_AttributeSelect":{"p":["DeepLink.Attribute","DeepLink.DeepLink"],"a":[]},"DeepLink.DS_Attribute":{"p":["DeepLink.DeepLink"],"a":[]},"DeepLink.ACT_MicroflowSelect":{"p":["DeepLink.Microflow","DeepLink.DeepLink"],"a":[]},"DeepLink.ACT_EntitySelect":{"p":["DeepLink.Entity","DeepLink.DeepLink"],"a":[]},"XLSReport.IVK_TemplateEdit":{"p":["XLSReport.MxTemplate"],"a":[]},"XLSReport.GenerateReport":{"p":["XLSReport.MxTemplate"],"a":null},"XLSReport.OCh_Xpath_RetrieveType":{"p":["XLSReport.MxXPath"],"a":[]},"XLSReport.DS_Constraint_attribute":{"p":["XLSReport.MxXPath"],"a":[["XLSReport.MxConstraint_MxXPath","XLSReport.MxXPath"]]},"XLSReport.DS_Constraint_reference":{"p":["XLSReport.MxXPath"],"a":[["XLSReport.MxConstraint_MxXPath","XLSReport.MxXPath"]]},"XLSReport.OCh_XPath_Refresh":{"p":["XLSReport.MxXPath"],"a":[]},"XLSReport.IVK_ConstraintSaveAndNext":{"p":["XLSReport.MxConstraint"],"a":[["XLSReport.MxConstraint_MxXPath","XLSReport.MxConstraint"],["XLSReport.MxConstraint_MxXPath","XLSReport.MxXPath"],["XLSReport.MxConstraint_MxSheet","XLSReport.MxConstraint"],["XLSReport.MxXPath_MxObjectReference","XLSReport.MxXPath"],["XLSReport.MxXPath_ParentMxXPath","XLSReport.MxXPath"],["XLSReport.MxXPath_MxObjectMember","XLSReport.MxXPath"]]},"XLSReport.IVK_ConstraintSave":{"p":["XLSReport.MxConstraint"],"a":[]},"XLSReport.DS_Sorting_attribute":{"p":["XLSReport.MxXPath"],"a":[["XLSReport.MxSorting_MxXPath","XLSReport.MxXPath"]]},"XLSReport.DS_Sorting_reference":{"p":["XLSReport.MxXPath"],"a":[["XLSReport.MxSorting_MxXPath","XLSReport.MxXPath"]]},"XLSReport.IVK_SortingSave":{"p":["XLSReport.MxSorting"],"a":[["XLSReport.MxSorting_MxXPath","XLSReport.MxSorting"],["XLSReport.MxSorting_MxSheet","XLSReport.MxSorting"],["XLSReport.MxXPath_MxObjectReference","XLSReport.MxXPath"],["XLSReport.MxXPath_ParentMxXPath","XLSReport.MxXPath"],["XLSReport.MxXPath_MxObjectMember","XLSReport.MxXPath"],["XLSReport.MxSorting_MxXPath","XLSReport.MxXPath"]]},"XLSReport.IVK_ExcistFile_Save":{"p":["XLSReport.CustomExcel"],"a":[]},"XLSReport.OCh_Template_Save":{"p":["XLSReport.MxTemplate"],"a":[]},"XLSReport.OCh_Sheet_Object":{"p":["XLSReport.MxSheet"],"a":[["XLSReport.MxSheet_MxObjectReference","XLSReport.MxSheet"]]},"XLSReport.OCh_Sheet_Reference":{"p":["XLSReport.MxSheet"],"a":[["XLSReport.MxSheet_MxObjectReference","XLSReport.MxSheet"]]},"XLSReport.Column_CSV_New":{"p":["XLSReport.MxSheet"],"a":[["XLSReport.MxXPath_MxData","XLSReport.MxData"],["XLSReport.MxXPath_MxData","XLSReport.MxXPath"]]},"XLSReport.IVK_DeleteColumn":{"p":["XLSReport.MxColumn"],"a":[]},"XLSReport.IVK_ColumnLower":{"p":["XLSReport.MxColumn"],"a":[["XLSReport.MxData_MxSheet","XLSReport.MxData"]]},"XLSReport.IVK_ColumnHigher":{"p":["XLSReport.MxColumn"],"a":[["XLSReport.MxData_MxSheet","XLSReport.MxData"]]},"XLSReport.IVK_ConstraintDelete":{"p":["XLSReport.MxConstraint"],"a":[]},"XLSReport.IVK_Constraint_Lower":{"p":["XLSReport.MxConstraint","XLSReport.MxSheet"],"a":[]},"XLSReport.IVK_Constraint_Higher":{"p":["XLSReport.MxConstraint","XLSReport.MxSheet"],"a":[]},"XLSReport.IVK_SortingDelete":{"p":["XLSReport.MxSorting"],"a":[]},"XLSReport.IVK_Sorting_Lower":{"p":["XLSReport.MxSorting","XLSReport.MxSheet"],"a":[]},"XLSReport.IVK_Sorting_Higher":{"p":["XLSReport.MxSorting","XLSReport.MxSheet"],"a":[]},"XLSReport.DS_TemplateCSVSheet":{"p":["XLSReport.MxTemplate"],"a":[]},"XLSReport.IVK_UploadExcistFile":{"p":["XLSReport.MxTemplate"],"a":[["XLSReport.MxTemplate_CustomExcel","XLSReport.MxTemplate"]]},"XLSReport.IVK_DeleteExcistFile":{"p":["XLSReport.MxTemplate"],"a":[["XLSReport.MxTemplate_CustomExcel","XLSReport.MxTemplate"]]},"XLSReport.IVK_CreateNewSheet":{"p":["XLSReport.MxTemplate"],"a":[["XLSReport.MxCellStyle_Template","XLSReport.MxTemplate"]]},"XLSReport.IVK_TemplateSaveAndNext":{"p":["XLSReport.MxTemplate"],"a":[]},"XLSReport.Static_New":{"p":["XLSReport.MxSheet"],"a":[["XLSReport.MxXPath_MxData","XLSReport.MxData"],["XLSReport.MxXPath_MxData","XLSReport.MxXPath"]]},"XLSReport.IVK_Column_New":{"p":["XLSReport.MxSheet"],"a":[["XLSReport.MxXPath_MxData","XLSReport.MxData"],["XLSReport.MxXPath_MxData","XLSReport.MxXPath"]]},"XLSReport.Sheet_Save":{"p":["XLSReport.MxSheet"],"a":[["XLSReport.MxData_MxSheet","XLSReport.MxSheet"]]},"XLSReport.DS_StaticInputMember":{"p":["XLSReport.MxStatic"],"a":[["XLSReport.MxData_MxSheet","XLSReport.MxData"],["XLSReport.MxSheet_Template","XLSReport.MxSheet"]]},"XLSReport.Static_Save":{"p":["XLSReport.MxStatic"],"a":[["XLSReport.MxData_MxSheet","XLSReport.MxData"]]},"XLSReport.DS_First_Attribute":{"p":["XLSReport.MxXPath"],"a":[["XLSReport.MxXPath_MxData","XLSReport.MxXPath"]]},"XLSReport.DS_First_Reference":{"p":["XLSReport.MxXPath"],"a":[["XLSReport.MxXPath_MxData","XLSReport.MxXPath"]]},"XLSReport.IVK_Column_Save":{"p":["XLSReport.MxColumn"],"a":[["XLSReport.MxData_MxSheet","XLSReport.MxData"],["XLSReport.MxXPath_MxData","XLSReport.MxData"],["XLSReport.MxXPath_MxData","XLSReport.MxXPath"],["XLSReport.MxXPath_MxObjectReference","XLSReport.MxXPath"],["XLSReport.MxXPath_ParentMxXPath","XLSReport.MxXPath"],["XLSReport.MxXPath_MxObjectMember","XLSReport.MxXPath"]]},"XLSReport.Settings_Save":{"p":["XLSReport.MxColumnSettings"],"a":[]},"XLSReport.DS_Attribute":{"p":["XLSReport.MxXPath"],"a":[["XLSReport.ChildMxXPath_MxXPath","XLSReport.MxXPath"]]},"XLSReport.DS_Reference":{"p":["XLSReport.MxXPath"],"a":[["XLSReport.ChildMxXPath_MxXPath","XLSReport.MxXPath"]]},"ExcelImporter.IVK_ImportTemplateDocument":{"p":["ExcelImporter.TemplateDocument"],"a":null},"ExcelImporter.Ch_Template_ChangeObjectType":{"p":["ExcelImporter.Template"],"a":[]},"ExcelImporter.Ch_Template_CheckNrs":{"p":["ExcelImporter.Template"],"a":[]},"ExcelImporter.Ch_FindMicroflow":{"p":["ExcelImporter.Column"],"a":[]},"ExcelImporter.Ch_SetMicroflow":{"p":["ExcelImporter.Column"],"a":[["ExcelImporter.Column_Microflows","ExcelImporter.Column"]]},"ExcelImporter.Ch_FindAttribute":{"p":["ExcelImporter.Column"],"a":[["ExcelImporter.Column_MxObjectType","ExcelImporter.Column"]]},"ExcelImporter.Ch_SetAttribute":{"p":["ExcelImporter.Column"],"a":[["ExcelImporter.Column_MxObjectMember","ExcelImporter.Column"]]},"ExcelImporter.Ch_FindReference":{"p":["ExcelImporter.Column"],"a":[["ExcelImporter.Column_MxObjectType","ExcelImporter.Column"],["ExcelImporter.Column_MxObjectType_Reference","ExcelImporter.Column"]]},"ExcelImporter.Ch_Column_SetDefaultObject":{"p":["ExcelImporter.Column"],"a":[["ExcelImporter.Column_MxObjectReference","ExcelImporter.Column"],["ExcelImporter.Column_MxObjectType","ExcelImporter.Column"],["ExcelImporter.Column_MxObjectType_Reference","ExcelImporter.Column"]]},"ExcelImporter.Ch_FindObjectType_Reference":{"p":["ExcelImporter.Column"],"a":[["ExcelImporter.Column_MxObjectReference","ExcelImporter.Column"]]},"ExcelImporter.Ch_SetObjectType_Reference":{"p":["ExcelImporter.Column"],"a":[["ExcelImporter.Column_MxObjectType_Reference","ExcelImporter.Column"]]},"ExcelImporter.Ch_FindAttribute_Reference":{"p":["ExcelImporter.Column"],"a":[["ExcelImporter.Column_MxObjectType_Reference","ExcelImporter.Column"]]},"ExcelImporter.Ch_SetAttribute_Reference":{"p":["ExcelImporter.Column"],"a":[["ExcelImporter.Column_MxObjectMember_Reference","ExcelImporter.Column"]]},"ExcelImporter.ExcelTemplate_ImportFromXml":{"p":["ExcelImporter.XMLDocumentTemplate"],"a":null},"ExcelImporter.IVK_Template_NewFromFile":{"p":[],"a":[]},"ExcelImporter.IVK_DuplicateTemplate":{"p":["ExcelImporter.Template"],"a":[["ExcelImporter.Template_AdditionalProperties","ExcelImporter.Template"]]},"ExcelImporter.ExcelTemplate_ExportToXML":{"p":["ExcelImporter.Template"],"a":null},"ExcelImporter.IVK_ImportXML_Upload":{"p":[],"a":[]},"ExcelImporter.IVK_SaveNewTemplate":{"p":["ExcelImporter.Template"],"a":[["ExcelImporter.ReferenceHandling_Template","ExcelImporter.Template"],["System.User_Language","System.User"],["ExcelImporter.Template_AdditionalProperties","ExcelImporter.Template"],["ExcelImporter.Template_AdditionalProperties","ExcelImporter.AdditionalProperties"]]},"ExcelImporter.IVK_SaveNewTemplate_CreateColumns":{"p":["ExcelImporter.Template"],"a":[["ExcelImporter.ReferenceHandling_Template","ExcelImporter.Template"],["System.User_Language","System.User"],["ExcelImporter.Template_AdditionalProperties","ExcelImporter.Template"],["ExcelImporter.Template_AdditionalProperties","ExcelImporter.AdditionalProperties"],["ExcelImporter.Template_MxObjectType","ExcelImporter.Template"],["ExcelImporter.Column_Template","ExcelImporter.Template"],["ExcelImporter.Column_MxObjectMember_Reference","ExcelImporter.Column"],["ExcelImporter.Column_MxObjectReference","ExcelImporter.Column"],["ExcelImporter.Column_MxObjectType_Reference","ExcelImporter.Column"],["ExcelImporter.Column_MxObjectMember","ExcelImporter.Column"],["ExcelImporter.Column_Template","ExcelImporter.Column"],["ExcelImporter.Column_MxObjectType","ExcelImporter.Column"],["ExcelImporter.Column_Microflows","ExcelImporter.Column"],["MxModelReflection.Microflows_InputParameter","MxModelReflection.Microflows"],["MxModelReflection.Microflows_Output_Type","MxModelReflection.Microflows"],["MxModelReflection.MxObjectMember_Type","MxModelReflection.MxObjectMember"]]},"ExcelImporter.IVK_CancelTemplate":{"p":["ExcelImporter.Template"],"a":[["ExcelImporter.Template_AdditionalProperties","ExcelImporter.AdditionalProperties"],["ExcelImporter.Template_AdditionalProperties","ExcelImporter.Template"],["ExcelImporter.Template_MasterTemplate","ExcelImporter.Template"],["ExcelImporter.Template_MxObjectType","MxModelReflection.MxObjectType"],["ExcelImporter.Template_MxObjectType","ExcelImporter.Template"],["ExcelImporter.Template_MxObjectReference_ParentAssociation","MxModelReflection.MxObjectReference"],["ExcelImporter.Template_MxObjectReference_ParentAssociation","ExcelImporter.Template"],["System.User_Language","System.User"]]},"ExcelImporter.IVK_ColumnNew":{"p":["ExcelImporter.Template"],"a":[]},"ExcelImporter.IVK_ColumnEdit":{"p":["ExcelImporter.Column","ExcelImporter.Template"],"a":[]},"ExcelImporter.IVK_Template_ConnectMatchingAttributes":{"p":["ExcelImporter.Template"],"a":[["ExcelImporter.Template_MxObjectType","ExcelImporter.Template"]]},"ExcelImporter.IVK_SaveTemplate":{"p":["ExcelImporter.Template"],"a":[["ExcelImporter.ReferenceHandling_Template","ExcelImporter.Template"],["System.User_Language","System.User"],["ExcelImporter.Template_AdditionalProperties","ExcelImporter.Template"],["ExcelImporter.Template_AdditionalProperties","ExcelImporter.AdditionalProperties"]]},"ExcelImporter.IVK_Column_Save":{"p":["ExcelImporter.Column"],"a":[["ExcelImporter.Column_MxObjectMember_Reference","ExcelImporter.Column"],["ExcelImporter.Column_MxObjectReference","ExcelImporter.Column"],["ExcelImporter.Column_MxObjectType_Reference","ExcelImporter.Column"],["ExcelImporter.Column_MxObjectMember","ExcelImporter.Column"],["ExcelImporter.Column_Template","ExcelImporter.Column"],["ExcelImporter.Column_MxObjectType","ExcelImporter.Column"],["ExcelImporter.Column_Microflows","ExcelImporter.Column"],["MxModelReflection.Microflows_InputParameter","MxModelReflection.Microflows"],["MxModelReflection.Microflows_Output_Type","MxModelReflection.Microflows"],["MxModelReflection.MxObjectMember_Type","MxModelReflection.MxObjectMember"]]},"ExcelImporter.IVK_SaveContinue_CreateTemplateFromDoc":{"p":["ExcelImporter.TemplateDocument"],"a":null},"ExcelImporter.IVK_TemplateDoc_Cancel":{"p":["ExcelImporter.TemplateDocument"],"a":[["ExcelImporter.TemplateDocument_Template","ExcelImporter.TemplateDocument"],["ExcelImporter.Template_AdditionalProperties","ExcelImporter.AdditionalProperties"],["ExcelImporter.Template_AdditionalProperties","ExcelImporter.Template"],["ExcelImporter.Template_MasterTemplate","ExcelImporter.Template"],["ExcelImporter.Template_MxObjectType","MxModelReflection.MxObjectType"],["ExcelImporter.Template_MxObjectType","ExcelImporter.Template"],["ExcelImporter.Template_MxObjectReference_ParentAssociation","MxModelReflection.MxObjectReference"],["ExcelImporter.Template_MxObjectReference_ParentAssociation","ExcelImporter.Template"],["ExcelImporter.TemplateDocument_Template","ExcelImporter.Template"]]},"Email_Connector.ACT_ShowAccountSettingsPage":{"p":["Email_Connector.EmailAccount"],"a":[["Email_Connector.IncomingEmailConfiguration_EmailAccount","Email_Connector.EmailAccount"],["Email_Connector.OutgoingEmailConfiguration_EmailAccount","Email_Connector.EmailAccount"],["Email_Connector.OutgoingEmailConfiguration_EmailAccount","Email_Connector.OutgoingEmailConfiguration"],["Email_Connector.IncomingEmailConfiguration_EmailAccount","Email_Connector.IncomingEmailConfiguration"]]},"Email_Connector.ACT_EmailAccount_RetrieveEmails":{"p":["Email_Connector.EmailAccount"],"a":null},"Email_Connector.ACT_EmailMessage_ComposeReply":{"p":["Email_Connector.EmailMessage","Email_Connector.EmailAccount"],"a":[]},"Email_Connector.ACT_EmailMessage_Delete":{"p":["Email_Connector.EmailMessage"],"a":[]},"Email_Connector.ACT_Attachment_Download":{"p":["Email_Connector.Attachment"],"a":[]},"Email_Connector.ACT_EmailMessage_SendComposedEmail":{"p":["Email_Connector.EmailMessage"],"a":null},"Email_Connector.ACT_Attachment_CreateNew":{"p":["Email_Connector.EmailMessage"],"a":[]},"Email_Connector.ACT_EmailMessage_ComposeNewEmail":{"p":["Email_Connector.EmailAccount"],"a":[]},"Email_Connector.ACT_OAuthProvider_ShowOAuthProviderPage":{"p":["Email_Connector.OAuthProvider"],"a":[["Email_Connector.EmailAccount_OAuthProvider","Email_Connector.OAuthProvider"]]},"Email_Connector.OCH_Pk12Certificate_DeleteCertificate":{"p":["Email_Connector.EmailAccount"],"a":[["Email_Connector.Pk12Certificate_EmailAccount","Email_Connector.EmailAccount"]]},"Email_Connector.DS_GetPKCS12Certificate":{"p":["Email_Connector.EmailAccount"],"a":[["Email_Connector.Pk12Certificate_EmailAccount","Email_Connector.EmailAccount"],["Email_Connector.Pk12Certificate_EmailAccount","Email_Connector.Pk12Certificate"]]},"Email_Connector.OCH_LDAPConfiguration_DeleteConfiguration":{"p":["Email_Connector.EmailAccount"],"a":[["Email_Connector.EmailAccount_LDAPConfiguration","Email_Connector.EmailAccount"]]},"Email_Connector.DS_GetLDAPConfiguration":{"p":["Email_Connector.EmailAccount"],"a":[["Email_Connector.EmailAccount_LDAPConfiguration","Email_Connector.EmailAccount"],["Email_Connector.EmailAccount_LDAPConfiguration","Email_Connector.LDAPConfiguration"]]},"Email_Connector.ACT_OAuthProvider_Create":{"p":[],"a":null},"Email_Connector.ACT_OAuthProvider_DeleteProvider":{"p":["Email_Connector.OAuthProvider"],"a":[]},"Email_Connector.SUB_EmailAccount_Delete":{"p":["Email_Connector.EmailAccount"],"a":[]},"Email_Connector.SUB_EmailAccount_Save":{"p":["Email_Connector.EmailAccount"],"a":null},"Email_Connector.ACT_SaveEmailAccountSettingAndClosePage":{"p":["Email_Connector.EmailAccount"],"a":null},"Email_Connector.ACT_EmailAccount_SaveEmailSecurityConfiguration":{"p":["Email_Connector.EmailAccount"],"a":[["Email_Connector.Pk12Certificate_EmailAccount","Email_Connector.EmailAccount"],["Email_Connector.Pk12Certificate_EmailAccount","Email_Connector.Pk12Certificate"],["Email_Connector.EmailAccount_LDAPConfiguration","Email_Connector.LDAPConfiguration"],["Email_Connector.EmailAccount_LDAPConfiguration","Email_Connector.EmailAccount"]]},"Email_Connector.OCH_IncomingEmailConfiguration_Select":{"p":["Email_Connector.EmailProvider"],"a":[["Email_Connector.IncomingServer_EmailProvider","Email_Connector.EmailProvider"],["Email_Connector.SelectedConfiguration_EmailProvider","Email_Connector.EmailProvider"],["Email_Connector.SelectedConfiguration_EmailProvider","Email_Connector.SelectedConfiguration"],["Email_Connector.IncomingServer_EmailProvider","Email_Connector.IncomingServer"]]},"Email_Connector.OEN_SetIncomingServer":{"p":["Email_Connector.IncomingServer"],"a":[["Email_Connector.IncomingServer_EmailProvider","Email_Connector.IncomingServer"],["Email_Connector.IncomingServer_EmailProvider","Email_Connector.EmailProvider"],["Email_Connector.SelectedConfiguration_EmailProvider","Email_Connector.EmailProvider"],["Email_Connector.SelectedConfiguration_EmailProvider","Email_Connector.SelectedConfiguration"]]},"Email_Connector.OCH_OutgoingEmailConfiguration_Select":{"p":["Email_Connector.EmailProvider"],"a":[["Email_Connector.OutgoingServer_EmailProvider","Email_Connector.EmailProvider"],["Email_Connector.SelectedConfiguration_EmailProvider","Email_Connector.EmailProvider"],["Email_Connector.SelectedConfiguration_EmailProvider","Email_Connector.SelectedConfiguration"],["Email_Connector.OutgoingServer_EmailProvider","Email_Connector.OutgoingServer"]]},"Email_Connector.OEN_SetOutgoingServer":{"p":["Email_Connector.OutgoingServer"],"a":[["Email_Connector.OutgoingServer_EmailProvider","Email_Connector.OutgoingServer"],["Email_Connector.OutgoingServer_EmailProvider","Email_Connector.EmailProvider"],["Email_Connector.SelectedConfiguration_EmailProvider","Email_Connector.EmailProvider"],["Email_Connector.SelectedConfiguration_EmailProvider","Email_Connector.SelectedConfiguration"]]},"Email_Connector.ACT_EmailMessageList_ResetQueuedStatus":{"p":["Email_Connector.EmailMessage"],"a":[]},"Email_Connector.ACT_EmailAccount_LaunchEmailConnectorOverview":{"p":[],"a":[]},"Email_Connector.ACT_EmailTemplate_DuplicateAndShowPage":{"p":["Email_Connector.EmailTemplate"],"a":null},"Email_Connector.OCH_EmailTemplate_ToggleRecipients":{"p":["Email_Connector.EmailTemplate"],"a":[]},"Email_Connector.ACT_EmailTemplate_GenerateAndSetPlainText":{"p":["Email_Connector.EmailTemplate"],"a":[]},"Email_Connector.ACT_EmailTemplate_ShowModelReflectionPage":{"p":["Email_Connector.EmailTemplate"],"a":[]},"Email_Connector.ACT_Emailtemplate_CreateToken":{"p":["Email_Connector.EmailTemplate"],"a":[["Email_Connector.EmailTemplate_Token","Email_Connector.EmailTemplate"],["MxModelReflection.Token_MxObjectType_Start","MxModelReflection.Token"]]},"Email_Connector.DS_ModelReflectionChecker":{"p":["Email_Connector.EmailTemplate"],"a":[]},"Email_Connector.ACT_EmailMessage_SendQueuedEmails":{"p":["Email_Connector.EmailAccount"],"a":null},"Email_Connector.OCH_OAuthProvider_SetCallbackURL_ClientCred":{"p":["Email_Connector.OAuthProvider"],"a":[]},"Email_Connector.OCH_OAuthProvider_SetCallbackURL_AuthCode":{"p":["Email_Connector.OAuthProvider"],"a":[]},"Email_Connector.OCH_EmailMessage_ToggleRecipients":{"p":["Email_Connector.EmailMessage"],"a":[]},"Email_Connector.VAL_Pk12Certificate":{"p":["Email_Connector.EmailMessage"],"a":[["Email_Connector.EmailMessage_EmailAccount","Email_Connector.EmailMessage"]]},"Email_Connector.VAL_LDAPConfiguration":{"p":["Email_Connector.EmailMessage"],"a":[["Email_Connector.EmailMessage_EmailAccount","Email_Connector.EmailMessage"]]},"Email_Connector.ACT_EmailTemplate_Save":{"p":["Email_Connector.EmailTemplate"],"a":[["Email_Connector.EmailTemplate_Token","Email_Connector.EmailTemplate"],["MxModelReflection.Token_MxObjectType_Start","MxModelReflection.Token"],["MxModelReflection.Token_MxObjectReference","MxModelReflection.Token"],["MxModelReflection.Token_MxObjectType_Referenced","MxModelReflection.Token"],["MxModelReflection.Token_MxObjectMember","MxModelReflection.Token"],["Email_Connector.Attachment_EmailTemplate","Email_Connector.EmailTemplate"]]},"Email_Connector.ACT_ShowAccountLoginPage":{"p":[],"a":[]},"Email_Connector.ACT_EmailAccount_SaveManualConfig":{"p":["Email_Connector.EmailAccount"],"a":null},"Email_Connector.ACT_EmailAccount_ClientCredentialsGrant_SaveManualConfig":{"p":["Email_Connector.EmailAccount"],"a":null},"Email_Connector.ACT_LDAPConfiguration_ChangeBaseName":{"p":["Email_Connector.LDAPBaseDN","Email_Connector.LDAPConfiguration"],"a":[]},"Email_Connector.DS_LDAPBaseDNList":{"p":["Email_Connector.LDAPConfiguration"],"a":null},"Email_Connector.OCH_OAuthProvider_CreateNew":{"p":["Email_Connector.EmailAccount"],"a":null},"Email_Connector.DS_EmailAccount_CreateDummyAccount":{"p":[],"a":[]},"Email_Connector.OCH_OAuthProvider_GetOrCreateOAuthProvider":{"p":["Email_Connector.EmailAccount"],"a":null},"Email_Connector.ACT_EmailMessage_SendEmailAndClosePage":{"p":["Email_Connector.EmailMessage"],"a":null},"Email_Connector.ACT_IncomingEmailConfiguration_FolderSelect":{"p":["Email_Connector.Folder","Email_Connector.IncomingEmailConfiguration"],"a":[]},"Email_Connector.DS_FolderList":{"p":["Email_Connector.IncomingEmailConfiguration"],"a":null},"Email_Connector.ACT_EmailAccount_SaveAutoConfig":{"p":["Email_Connector.EmailProvider"],"a":null},"Email_Connector.ACT_EmailAccount_ClientCredentialsGrant_SaveAutoConfig":{"p":["Email_Connector.EmailProvider"],"a":null},"Email_Connector.ACT_OAuthProvider_Save":{"p":["Email_Connector.OAuthProvider"],"a":[["Email_Connector.ScopeSelected_OAuthProvider","Email_Connector.OAuthProvider"]]},"Email_Connector.ACT_SelectedConfiguration_FetchEmailServerConfigAndShowConfigPage":{"p":["Email_Connector.EmailAccount"],"a":[["Email_Connector.EmailAccount_OAuthProvider","Email_Connector.EmailAccount"],["Email_Connector.SelectedConfiguration_EmailProvider","Email_Connector.EmailProvider"],["Email_Connector.SelectedConfiguration_EmailProvider","Email_Connector.SelectedConfiguration"]]},"Email_Connector.ACT_IncomingEmailConfiguration_ChangeMoveToFolder":{"p":["Email_Connector.Folder","Email_Connector.IncomingEmailConfiguration"],"a":[]},"Rencar.NAV_Dashboard_Open":{"p":[],"a":[]},"Administration.ManageMyAccount":{"p":[],"a":[]},"DeepLink.SUB_GetApplicationURL":{"p":[],"a":[]},"DeepLink.GetMicroflowInputParametersAsQueryString":{"p":[],"a":[]},"DeepLink.GetExampleObject":{"p":["DeepLink.DeepLink"],"a":[]},"Email_Connector.SUB_GetOAuthURL":{"p":["Email_Connector.EmailAccount"],"a":[["Email_Connector.EmailAccount_OAuthProvider","Email_Connector.EmailAccount"],["Email_Connector.ScopeSelected_OAuthProvider","Email_Connector.OAuthProvider"]]}}